littlefish/__init__.py
littlefish/ansi.py
littlefish/attackprotect.py
littlefish/celeryutil.py
littlefish/colourutil.py
littlefish/contentscanner.py
littlefish/dbutil.py
littlefish/debuglog.py
littlefish/debugtools.py
littlefish/encoder.py
littlefish/enumeration.py
littlefish/fileutil.py
littlefish/geoip.py
littlefish/healthcheck.py
littlefish/hostidentifier.py
littlefish/htmlutil.py
littlefish/imageutil.py
littlefish/json.py
littlefish/lfsmailer.py
littlefish/loggingutil.py
littlefish/pager.py
littlefish/pdfsigner.py
littlefish/postgresping.py
littlefish/randomtext.py
littlefish/redisutil.py
littlefish/simpleserver.py
littlefish/sslutil.py
littlefish/timetool.py
littlefish/util.py
littlefish/validation.py
littlefish/viewutil.py
littlefish/warninglog.py
littlefish/xmlutil.py
littlefish/yamldata.py
littlefish/background/__init__.py
littlefish/background/emailqueue.py
littlefish/background/systemevent.py
littlefish/sessiondata/__init__.py
littlefish/sessiondata/framework.py
littlefish/sessiondata/sessionvars.py
littlefish/test_data/markov.dat
littlefish-0.0.75.dist-info/LICENSE.txt
littlefish-0.0.75.dist-info/METADATA
littlefish-0.0.75.dist-info/WHEEL
littlefish-0.0.75.dist-info/top_level.txt
littlefish-0.0.75.dist-info/RECORD
